seapipy/__init__.py
seapipy/command.py
seapipy/example_tissues.py
seapipy/lattice_class.py
seapipy/surface_evolver.py
seapipy-0.2.1.dist-info/LICENSE
seapipy-0.2.1.dist-info/METADATA
seapipy-0.2.1.dist-info/WHEEL
seapipy-0.2.1.dist-info/top_level.txt
seapipy-0.2.1.dist-info/RECORD
