Metadata-Version: 2.1
Name: seapipy
Version: 0.2.1
Summary: A Surface evolver API for python
Author-email: Augusto Borges <borges.augustoar@gmail.com>
License: BSD 3-Clause License
Project-URL: Homepage, https://github.com/borgesaugusto/seapipy/
Keywords: Surface Evolver,API,Vertex model
Classifier: Intended Audience :: Science/Research
Requires-Python: >=3.9
License-File: LICENSE
Requires-Dist: matplotlib >=3.6.2
Requires-Dist: numpy >=1.23.4
Requires-Dist: scipy >=1.9.3
Requires-Dist: setuptools >=60.2.0
Requires-Dist: tomli ; python_version < "3.11"
Provides-Extra: test
Requires-Dist: pytest >=7.2.0 ; extra == 'test'
